pycoornet/__init__.py
pycoornet/crowdtangle.py
pycoornet/shared.py
pycoornet/statistics.py
pycoornet/utils.py
pycoornet-0.6.0.dist-info/LICENSE
pycoornet-0.6.0.dist-info/METADATA
pycoornet-0.6.0.dist-info/WHEEL
pycoornet-0.6.0.dist-info/top_level.txt
pycoornet-0.6.0.dist-info/RECORD
