Metadata-Version: 2.1
Name: pycoornet
Version: 0.6.0
Summary: Using Python Given a set of URLs, this packages detects coordinated link sharing behavior on social media and outputs the network of entities that performed such behaviour.
Home-page: https://github.com/UPB-SS1/PyCooRnet
Author: Camilo Andres Soto Montoya, Jose R. Zapata
Author-email: camilo.soto@outlook.com, jjrzg@hotmail.com
License: MIT
Keywords: pyCooRnet
Platform: UNKNOWN
Classifier: Programming Language :: Python :: 3
Classifier: License :: OSI Approved :: MIT License
Classifier: Operating System :: OS Independent
Requires-Python: >=3.6
Requires-Dist: pandas (>=1.0.5)
Requires-Dist: PyCrowdTangle (>=0.5.0)
Requires-Dist: tqdm (>=4.47.0)
Requires-Dist: networkx (>=2.4)
Requires-Dist: python-louvain (>=0.14)
Requires-Dist: tldextract (>=3.1.0)
Requires-Dist: pyarrow (>=4.0.0)
Requires-Dist: ratelimiter (>=1.2.0)
